abf/__init__.py
abf/_version.py
abf/bundle.py
abf/cli.py
abf/errors.py
abf/py.typed
abf/repository.py
abf/workspace.py
abf/abstracts/__init__.py
abf/abstracts/acceptance_validation.py
abf/abstracts/action.py
abf/abstracts/param_validation.py
abf/abstracts/plan_validation.py
abf/utils/__init__.py
abf/utils/aws.py
tests/__init__.py
tests/settings.py
tests/test_bundle.py
tests/test_repository.py
tests/test_workspace.py
tests/abstracts/__init__.py
tests/abstracts/test_action.py
tests/abstracts/test_aws.py
tests/abstracts/test_param_validation.py
tests/abstracts/test_plan_validation.py
AssetBundleFramework-0.3.0.dist-info/METADATA
AssetBundleFramework-0.3.0.dist-info/WHEEL
AssetBundleFramework-0.3.0.dist-info/entry_points.txt
AssetBundleFramework-0.3.0.dist-info/top_level.txt
AssetBundleFramework-0.3.0.dist-info/RECORD
