Metadata-Version: 2.1
Name: AssetBundleFramework
Version: 0.3.0
Summary: Framework for managing Aptible Asset Bundles
License: MIT
Requires-Dist: boto3
Requires-Dist: semver (<3,>2)
Requires-Dist: pydantic (<2,>=1.9.0)
Requires-Dist: terrapyst
Requires-Dist: ruamel.yaml
Requires-Dist: typer
Provides-Extra: dev
Requires-Dist: black ; extra == 'dev'
Requires-Dist: build ; extra == 'dev'
Requires-Dist: isort ; extra == 'dev'
Requires-Dist: mypy ; extra == 'dev'
Requires-Dist: pytest ; extra == 'dev'
Requires-Dist: pytest-cov ; extra == 'dev'
Requires-Dist: types-PyYAML ; extra == 'dev'
Requires-Dist: boto3-stubs ; extra == 'dev'
Requires-Dist: versioneer ; extra == 'dev'
